Thread_Warden/Data_Containers.py
Thread_Warden/Interfaces.py
Thread_Warden/Thread_Warden.py
Thread_Warden/__init__.py
thread_warden-0.1.0.dist-info/licenses/LICENSE
thread_warden-0.1.0.dist-info/METADATA
thread_warden-0.1.0.dist-info/WHEEL
thread_warden-0.1.0.dist-info/top_level.txt
thread_warden-0.1.0.dist-info/RECORD
