Metadata-Version: 2.4
Name: thread-warden
Version: 0.1.0
Summary: A robust thread supervisor for Python applications that monitors, restarts, and manages state for threads.
Author: Seth Michel
License: MIT License
Project-URL: Homepage, https://github.com/SethMichel/thread-warden
Project-URL: Bug Tracker, https://github.com/SethMichel/thread-warden/issues
Classifier: Programming Language :: Python :: 3
Classifier: License :: OSI Approved :: MIT License
Classifier: Operating System :: OS Independent
Requires-Python: >=3.8
License-File: LICENSE
Dynamic: license-file
